oeg_infotech/__init__.py
oeg_infotech/base.py
oeg_infotech/defect.py
oeg_infotech/lineobj.py
oeg_infotech/ordered_attrib.py
oeg_infotech/pigpass.py
oeg_infotech/weld.py
oeg_infotech/codes/__init__.py
oeg_infotech/codes/company.py
oeg_infotech/codes/feature.py
oeg_infotech/codes/kbd.py
oeg_infotech/codes/passtype.py
oeg_infotech/codes/pigtype.py
oeg_infotech/codes/tube.py
oeg_infotech-1.5.dist-info/LICENSE
oeg_infotech-1.5.dist-info/METADATA
oeg_infotech-1.5.dist-info/WHEEL
oeg_infotech-1.5.dist-info/top_level.txt
oeg_infotech-1.5.dist-info/RECORD
