Metadata-Version: 2.1
Name: oeg-infotech
Version: 1.5
Summary: Library for OrgEnergoGaz Infotech xml processing
Home-page: https://github.com/vb64/oeg.infotech.xml
Author: Vitaly Bogomolov
Author-email: mail@vitaly-bogomolov.ru
License: UNKNOWN
Download-URL: https://github.com/vb64/oeg.infotech.xml/archive/v1.5.tar.gz
Keywords: python,OrgEnergoGaz,Infotech,IUST,xml
Platform: UNKNOWN
Classifier: Programming Language :: Python
Classifier: License :: OSI Approved :: MIT License
Classifier: Operating System :: OS Independent
